pybibx/__init__.py
pybibx/base/__init__.py
pybibx/base/pbx.py
pybibx/base/stws/Stopwords-Arabic.txt
pybibx/base/stws/Stopwords-Bengali.txt
pybibx/base/stws/Stopwords-Bulgarian.txt
pybibx/base/stws/Stopwords-Chinese.txt
pybibx/base/stws/Stopwords-Czech.txt
pybibx/base/stws/Stopwords-English.txt
pybibx/base/stws/Stopwords-Finnish.txt
pybibx/base/stws/Stopwords-French.txt
pybibx/base/stws/Stopwords-German.txt
pybibx/base/stws/Stopwords-Greek.txt
pybibx/base/stws/Stopwords-Hebrew.txt
pybibx/base/stws/Stopwords-Hindi.txt
pybibx/base/stws/Stopwords-Hungarian.txt
pybibx/base/stws/Stopwords-Italian.txt
pybibx/base/stws/Stopwords-Japanese.txt
pybibx/base/stws/Stopwords-Korean.txt
pybibx/base/stws/Stopwords-Marathi.txt
pybibx/base/stws/Stopwords-Persian.txt
pybibx/base/stws/Stopwords-Polish.txt
pybibx/base/stws/Stopwords-Portuguese-br.txt
pybibx/base/stws/Stopwords-Romanian.txt
pybibx/base/stws/Stopwords-Russian.txt
pybibx/base/stws/Stopwords-Slovak.txt
pybibx/base/stws/Stopwords-Spanish.txt
pybibx/base/stws/Stopwords-Swedish.txt
pybibx/base/stws/Stopwords-Thai.txt
pybibx/base/stws/Stopwords-Ukrainian.txt
pybibx/base/stws/__init__.py
pybibx-5.2.5.dist-info/LICENSE
pybibx-5.2.5.dist-info/METADATA
pybibx-5.2.5.dist-info/WHEEL
pybibx-5.2.5.dist-info/top_level.txt
pybibx-5.2.5.dist-info/zip-safe
pybibx-5.2.5.dist-info/RECORD
