Metadata-Version: 2.1
Name: pybibx
Version: 5.2.5
Summary: A Bibliometric and Scientometric Library Powered with Artificial Intelligence Tools
Home-page: https://github.com/Valdecy/pybibx
Author: Valdecy Pereira
Author-email: valdecy.pereira@gmail.com
License: GNU
License-File: LICENSE
Requires-Dist: bertopic
Requires-Dist: bert-extractive-summarizer
Requires-Dist: chardet
Requires-Dist: google-generativeai
Requires-Dist: gensim
Requires-Dist: keybert
Requires-Dist: llmx
Requires-Dist: matplotlib
Requires-Dist: networkx
Requires-Dist: numba
Requires-Dist: numpy
Requires-Dist: pandas
Requires-Dist: Pillow
Requires-Dist: plotly
Requires-Dist: scipy
Requires-Dist: scikit-learn
Requires-Dist: sentencepiece
Requires-Dist: sentence-transformers
Requires-Dist: torch
Requires-Dist: torchvision
Requires-Dist: torchaudio
Requires-Dist: transformers
Requires-Dist: umap-learn
Requires-Dist: openai
Requires-Dist: wordcloud
